collibra_catalog_sampling/__init__.py
collibra_catalog_sampling/api_client.py
collibra_catalog_sampling/configuration.py
collibra_catalog_sampling/rest.py
collibra_catalog_sampling/api/__init__.py
collibra_catalog_sampling/api/samples_api.py
collibra_catalog_sampling/models/__init__.py
collibra_catalog_sampling/models/column_paged_response.py
collibra_catalog_sampling/models/job.py
collibra_catalog_sampling/models/read_samples_response.py
collibra_catalog_sampling/models/request_samples_response.py
collibra_catalog_sampling/models/sample_column.py
collibra_catalog_sampling/models/standard_error_response.py
test/__init__.py
test/test_column_paged_response.py
test/test_job.py
test/test_read_samples_response.py
test/test_request_samples_response.py
test/test_sample_column.py
test/test_samples_api.py
test/test_standard_error_response.py
collibra_catalog_sampling_100-1.0.0.dist-info/METADATA
collibra_catalog_sampling_100-1.0.0.dist-info/WHEEL
collibra_catalog_sampling_100-1.0.0.dist-info/top_level.txt
collibra_catalog_sampling_100-1.0.0.dist-info/RECORD
