Metadata-Version: 2.1
Name: collibra-catalog-sampling-100
Version: 1.0.0
Summary: Catalog Sampling API
Home-page: 
Author-email: 
Keywords: Swagger,Catalog Sampling API
Requires-Dist: urllib3 (>=1.15)
Requires-Dist: six (>=1.10)
Requires-Dist: certifi
Requires-Dist: python-dateutil
